{
  "type": "Feature",
  "properties": {
    "gn:admin1_code":"VG",
    "gn:admin2_code":"34",
    "gn:asciiname":"Jansagerdi",
    "gn:country_code":"FO",
    "gn:dem":205,
    "gn:feature_class":"P",
    "gn:feature_code":"PPL",
    "gn:name":"Jansager\u00f0i",
    "gn:population":0,
    "gn:timezone":"Atlantic/Faroe",
    "iso:country":"FO",
    "name:und_x_variant":[
        "Iansager\u00f0i",
        "Jansager\u00f0i",
        "Jenseg\u00e6rde"
    ],
    "wof:name":"Jansagerdi",
    "wof:placetype":"locality"
},
  "geometry": {"coordinates":[-7.18592,62.04385],"type":"Point"}
}