{
  "type": "Feature",
  "properties": {
    "gn:gn_country":"FO",
    "gn:gn_fcode":"PPL",
    "gn:gn_pop":71,
    "gn:population":71,
    "iso:country":"FO",
    "name:dan_x_preferred":[
        "Selatra\u00f0"
    ],
    "name:dut_x_preferred":[
        "Selatra\u00f0"
    ],
    "name:eng_x_preferred":[
        "Selatra\u00f0"
    ],
    "name:fao_x_preferred":[
        "Selatra\u00f0"
    ],
    "name:fre_x_preferred":[
        "Selatra\u00f0"
    ],
    "name:ger_x_preferred":[
        "Selatra\u00f0"
    ],
    "name:hun_x_preferred":[
        "Selatra\u00f0"
    ],
    "name:nob_x_preferred":[
        "Selatra\u00f0"
    ],
    "name:rum_x_preferred":[
        "Selatra\u00f0"
    ],
    "name:swe_x_preferred":[
        "Selatra\u00f0"
    ],
    "name:unk_x_variant":[
        "Selletr\u00e6"
    ],
    "qs_pg:aaroncc":"FO",
    "qs_pg:gn_country":"FO",
    "qs_pg:gn_fcode":"PPL",
    "qs_pg:gn_pop":71,
    "qs_pg:name":"Selatra\u00ff",
    "qs_pg:name_adm0":"F\u00e6r\u00f8erne",
    "qs_pg:name_adm1":"Sy\u00f0ra Eysturoy",
    "qs_pg:photos":34,
    "qs_pg:photos_1k":7,
    "qs_pg:photos_9k":1,
    "qs_pg:photos_9r":2,
    "qs_pg:photos_all":34,
    "qs_pg:photos_sr":2,
    "qs_pg:pop_sr":1,
    "qs_pg:qs_pg_placetype":"locality",
    "qs_pg:qs_pg_placetype_gp":"Town",
    "qs_pg:woe_adm0":23424816,
    "woe:adm0_id":23424816,
    "woe:name_adm0":"F\u00e6r\u00f8erne",
    "woe:name_adm1":"Sy\u00f0ra Eysturoy",
    "woe:placetype":"Town",
    "wof:name":"Selatra\u00ff",
    "wof:placetype":"locality",
    "wof:population":71
},
  "geometry": {"coordinates":[-6.87163,62.15637],"type":"Point"}
}