{
  "type": "Feature",
  "properties": {
    "gn:admin1_code":"SU",
    "gn:admin2_code":"50",
    "gn:asciiname":"Leiti",
    "gn:country_code":"FO",
    "gn:dem":218,
    "gn:feature_class":"P",
    "gn:feature_code":"PPL",
    "gn:name":"Leiti",
    "gn:population":0,
    "gn:timezone":"Atlantic/Faroe",
    "iso:country":"FO",
    "wof:name":"Leiti",
    "wof:placetype":"locality"
},
  "geometry": {"coordinates":[-6.75167,61.44996999999999],"type":"Point"}
}