{
  "type": "Feature",
  "properties": {
    "gn:gn_country":"FO",
    "gn:gn_fcode":"PPL",
    "gn:gn_pop":14,
    "gn:population":14,
    "iso:country":"FO",
    "name:dan_x_preferred":[
        "Sy\u00f0radalur"
    ],
    "name:deu_x_preferred":[
        "Sy\u00f0radalur"
    ],
    "name:eng_x_preferred":[
        "Sy\u00f0radalur"
    ],
    "name:fao_x_preferred":[
        "Sy\u00f0radalur"
    ],
    "name:fra_x_preferred":[
        "Sy\u00f0radalur"
    ],
    "name:hun_x_preferred":[
        "Sy\u00f0radalur"
    ],
    "name:nld_x_preferred":[
        "Sy\u00f0radalur"
    ],
    "name:nob_x_preferred":[
        "Sy\u00f0radalur"
    ],
    "name:pol_x_preferred":[
        "Sy\u00f0radalur"
    ],
    "name:ron_x_preferred":[
        "Sy\u00f0radalur"
    ],
    "name:slk_x_preferred":[
        "Sy\u00f0radalur"
    ],
    "name:spa_x_preferred":[
        "Sy\u00f0radalur"
    ],
    "name:swe_x_preferred":[
        "Sy\u00f0radalur"
    ],
    "name:unk_x_variant":[
        "Sydredal"
    ],
    "qs_pg:aaroncc":"FO",
    "qs_pg:gn_country":"FO",
    "qs_pg:gn_fcode":"PPL",
    "qs_pg:gn_pop":14,
    "qs_pg:name":"Sy\u00ffradalur",
    "qs_pg:name_adm0":"F\u00e6r\u00f8erne",
    "qs_pg:name_adm1":"Nor\u00f0oy",
    "qs_pg:photos_9k":1,
    "qs_pg:photos_9r":1,
    "qs_pg:photos_all":2,
    "qs_pg:photos_sr":0,
    "qs_pg:pop_sr":1,
    "qs_pg:qs_pg_placetype":"locality",
    "qs_pg:qs_pg_placetype_gp":"Town",
    "qs_pg:woe_adm0":23424816,
    "woe:adm0_id":23424816,
    "woe:name_adm0":"F\u00e6r\u00f8erne",
    "woe:name_adm1":"Nor\u00f0oy",
    "woe:placetype":"Town",
    "wof:name":"Sy\u00ffradalur",
    "wof:placetype":"locality",
    "wof:population":14
},
  "geometry": {"coordinates":[-6.66057,62.245],"type":"Point"}
}