{
  "type": "Feature",
  "properties": {
    "gn:country":"FO",
    "gn:fcode":"PPL",
    "gn:population":30,
    "iso:country":"FO",
    "name:cat_x_preferred":[
        "Sv\u00edn\u00e1ir"
    ],
    "name:dan_x_preferred":[
        "Sv\u00edn\u00e1ir"
    ],
    "name:deu_x_preferred":[
        "Sv\u00edn\u00e1ir"
    ],
    "name:eng_x_preferred":[
        "Sv\u00edn\u00e1ir"
    ],
    "name:fao_x_preferred":[
        "Sv\u00edn\u00e1ir"
    ],
    "name:fra_x_preferred":[
        "Sv\u00edn\u00e1ir"
    ],
    "name:hun_x_preferred":[
        "Sv\u00edn\u00e1ir"
    ],
    "name:nld_x_preferred":[
        "Sv\u00edn\u00e1ir"
    ],
    "name:nob_x_preferred":[
        "Sv\u00edn\u00e1ir"
    ],
    "name:pol_x_preferred":[
        "Sv\u00edn\u00e1ir"
    ],
    "name:ron_x_preferred":[
        "Sv\u00edn\u00e1ir"
    ],
    "name:swe_x_preferred":[
        "Sv\u00edn\u00e1ir"
    ],
    "name:und_x_variant":[
        "Svin\u00e5er"
    ],
    "qs_pg:aaroncc":"FO",
    "qs_pg:gn_country":"FO",
    "qs_pg:gn_fcode":"PPL",
    "qs_pg:gn_pop":30,
    "qs_pg:name":"Sv\u00edn\u00e1ir",
    "qs_pg:name_adm0":"F\u00e6r\u00f8erne",
    "qs_pg:name_adm1":"Nor\u00f0ara Eysturoy",
    "qs_pg:photos_9k":1,
    "qs_pg:photos_9r":2,
    "qs_pg:photos_all":64,
    "qs_pg:photos_sr":0,
    "qs_pg:pop_sr":1,
    "qs_pg:qs_pg_placetype":"locality",
    "qs_pg:qs_pg_placetype_gp":"Town",
    "qs_pg:woe_adm0":23424816,
    "woe:adm0_id":23424816,
    "woe:name_adm0":"F\u00e6r\u00f8erne",
    "woe:name_adm1":"Nor\u00f0ara Eysturoy",
    "woe:placetype":"Town",
    "wof:name":"Sv\u00edn\u00e1ir",
    "wof:placetype":"locality",
    "wof:population":30
},
  "geometry": {"coordinates":[-7.02842,62.23164],"type":"Point"}
}