{
  "type": "Feature",
  "properties": {
    "gn:gn_country":"FO",
    "gn:gn_fcode":"PPL",
    "gn:gn_pop":45,
    "gn:population":45,
    "iso:country":"FO",
    "name:dan_x_preferred":[
        "Dalur"
    ],
    "name:dut_x_preferred":[
        "Dalur"
    ],
    "name:eng_x_preferred":[
        "Dalur"
    ],
    "name:epo_x_preferred":[
        "Dalur"
    ],
    "name:fao_x_preferred":[
        "Dalur"
    ],
    "name:fre_x_preferred":[
        "Dalur"
    ],
    "name:ger_x_preferred":[
        "Dalur"
    ],
    "name:hun_x_preferred":[
        "Dalur"
    ],
    "name:nob_x_preferred":[
        "Dalur"
    ],
    "name:pol_x_preferred":[
        "Dalur"
    ],
    "name:rum_x_preferred":[
        "Dalur"
    ],
    "name:swe_x_preferred":[
        "Dalur"
    ],
    "name:unk_x_variant":[
        "Dal"
    ],
    "qs_pg:aaroncc":"FO",
    "qs_pg:gn_country":"FO",
    "qs_pg:gn_fcode":"PPL",
    "qs_pg:gn_pop":45,
    "qs_pg:name":"Dalur",
    "qs_pg:name_adm0":"F\u00e6r\u00f8erne",
    "qs_pg:name_adm1":"Sandoy",
    "qs_pg:photos_9k":1,
    "qs_pg:photos_9r":1,
    "qs_pg:photos_all":2,
    "qs_pg:photos_sr":0,
    "qs_pg:pop_sr":1,
    "qs_pg:qs_pg_placetype":"locality",
    "qs_pg:qs_pg_placetype_gp":"Town",
    "qs_pg:woe_adm0":23424816,
    "woe:adm0_id":23424816,
    "woe:name_adm0":"F\u00e6r\u00f8erne",
    "woe:name_adm1":"Sandoy",
    "woe:placetype":"Town",
    "wof:name":"Dalur",
    "wof:placetype":"locality",
    "wof:population":45
},
  "geometry": {"coordinates":[-6.67153,61.78456],"type":"Point"}
}