{
  "type": "Feature",
  "properties": {
    "gn:country":"FO",
    "gn:fcode":"PPL",
    "gn:population":3,
    "iso:country":"FO",
    "name:bar_x_preferred":[
        "Sund"
    ],
    "name:cat_x_preferred":[
        "Sund"
    ],
    "name:dan_x_preferred":[
        "Sund"
    ],
    "name:deu_x_preferred":[
        "Sund"
    ],
    "name:eng_x_preferred":[
        "Sund"
    ],
    "name:fao_x_preferred":[
        "Sund"
    ],
    "name:hun_x_preferred":[
        "Sund"
    ],
    "name:nld_x_preferred":[
        "Sund"
    ],
    "name:nob_x_preferred":[
        "Sund"
    ],
    "name:ron_x_preferred":[
        "Sund"
    ],
    "name:spa_x_preferred":[
        "Sund"
    ],
    "name:swe_x_preferred":[
        "Sund"
    ],
    "qs_pg:aaroncc":"FO",
    "qs_pg:gn_country":"FO",
    "qs_pg:gn_fcode":"PPL",
    "qs_pg:gn_pop":3,
    "qs_pg:name":"Sund",
    "qs_pg:name_adm0":"F\u00e6r\u00f8erne",
    "qs_pg:name_adm1":"Streymoy",
    "qs_pg:photos":104,
    "qs_pg:photos_1k":21,
    "qs_pg:photos_9k":1,
    "qs_pg:photos_9r":3,
    "qs_pg:photos_all":104,
    "qs_pg:photos_sr":3,
    "qs_pg:pop_sr":1,
    "qs_pg:qs_pg_placetype":"locality",
    "qs_pg:qs_pg_placetype_gp":"Town",
    "qs_pg:woe_adm0":23424816,
    "woe:adm0_id":23424816,
    "woe:name_adm0":"F\u00e6r\u00f8erne",
    "woe:name_adm1":"Streymoy",
    "woe:placetype":"Town",
    "wof:name":"Sund",
    "wof:placetype":"locality",
    "wof:population":3
},
  "geometry": {"coordinates":[-6.83661,62.04728],"type":"Point"}
}