{
  "type": "Feature",
  "properties": {
    "gn:gn_country":"FO",
    "gn:gn_fcode":"PPL",
    "gn:gn_pop":206,
    "gn:population":206,
    "iso:country":"FO",
    "name:dan_x_preferred":[
        "Oyndarfj\u00f8r\u00f0ur"
    ],
    "name:dut_x_preferred":[
        "Oyndarfj\u00f8r\u00f0ur"
    ],
    "name:eng_x_preferred":[
        "Oyndarfj\u00f8r\u00f0ur"
    ],
    "name:fao_x_preferred":[
        "Oyndarfj\u00f8r\u00f0ur"
    ],
    "name:fre_x_preferred":[
        "Oyndarfj\u00f8r\u00f0ur"
    ],
    "name:ger_x_preferred":[
        "Oyndarfj\u00f8r\u00f0ur"
    ],
    "name:hun_x_preferred":[
        "Oyndarfj\u00f8r\u00f0ur"
    ],
    "name:nob_x_preferred":[
        "Oyndarfj\u00f8r\u00f0ur"
    ],
    "name:rum_x_preferred":[
        "Oyndarfj\u00f8r\u00f0ur"
    ],
    "name:swe_x_preferred":[
        "Oyndarfj\u00f8r\u00f0ur"
    ],
    "name:unk_x_variant":[
        "Andefjord"
    ],
    "qs_pg:aaroncc":"FO",
    "qs_pg:gn_country":"FO",
    "qs_pg:gn_fcode":"PPL",
    "qs_pg:gn_pop":206,
    "qs_pg:name":"Oyndarfj\u00f8r\u00f0ur",
    "qs_pg:photos_9r":0,
    "qs_pg:photos_sr":0,
    "qs_pg:pop_sr":2,
    "qs_pg:qs_pg_placetype":"locality",
    "wof:name":"Oyndarfj\u00f8r\u00f0ur",
    "wof:placetype":"locality",
    "wof:population":206
},
  "geometry": {"coordinates":[-6.84643,62.27792],"type":"Point"}
}