{
  "type": "Feature",
  "properties": {
    "gn:gn_country":"FO",
    "gn:gn_fcode":"PPL",
    "gn:gn_pop":148,
    "gn:population":148,
    "iso:country":"FO",
    "name:dan_x_preferred":[
        "Velbasta\u00f0ur"
    ],
    "name:dut_x_preferred":[
        "Velbasta\u00f0ur"
    ],
    "name:eng_x_preferred":[
        "Velbasta\u00f0ur"
    ],
    "name:fao_x_preferred":[
        "Velbasta\u00f0ur"
    ],
    "name:fre_x_preferred":[
        "Velbasta\u00f0ur"
    ],
    "name:ger_x_preferred":[
        "Velbasta\u00f0ur"
    ],
    "name:hun_x_preferred":[
        "Velbasta\u00f0ur"
    ],
    "name:nob_x_preferred":[
        "Velbasta\u00f0ur"
    ],
    "name:per_x_preferred":[
        "\u0648\u0644\u0628\u0633\u062a\u062a\u0648\u0631"
    ],
    "name:rum_x_preferred":[
        "Velbasta\u00f0ur"
    ],
    "name:spa_x_preferred":[
        "Velbasta\u00f0ur"
    ],
    "name:swe_x_preferred":[
        "Velbasta\u00f0ur"
    ],
    "name:unk_x_variant":[
        "Velbestad"
    ],
    "qs_pg:aaroncc":"FO",
    "qs_pg:gn_country":"FO",
    "qs_pg:gn_fcode":"PPL",
    "qs_pg:gn_pop":148,
    "qs_pg:name":"Velbasta\u00ffur",
    "qs_pg:name_adm0":"F\u00e6r\u00f8erne",
    "qs_pg:name_adm1":"Streymoy",
    "qs_pg:photos":130,
    "qs_pg:photos_1k":26,
    "qs_pg:photos_9k":1,
    "qs_pg:photos_9r":3,
    "qs_pg:photos_all":130,
    "qs_pg:photos_sr":3,
    "qs_pg:pop_sr":1,
    "qs_pg:qs_pg_placetype":"locality",
    "qs_pg:qs_pg_placetype_gp":"Town",
    "qs_pg:woe_adm0":23424816,
    "woe:adm0_id":23424816,
    "woe:name_adm0":"F\u00e6r\u00f8erne",
    "woe:name_adm1":"Streymoy",
    "woe:placetype":"Town",
    "wof:name":"Velbasta\u00ffur",
    "wof:placetype":"locality",
    "wof:population":148
},
  "geometry": {"coordinates":[-6.85258,61.98084],"type":"Point"}
}