{
  "type": "Feature",
  "properties": {
    "gn:gn_country":"FO",
    "gn:gn_fcode":"PPL",
    "gn:gn_pop":4,
    "gn:population":4,
    "iso:country":"FO",
    "name:dan_x_preferred":[
        "M\u00fali"
    ],
    "name:dut_x_preferred":[
        "M\u00fali"
    ],
    "name:eng_x_preferred":[
        "M\u00fali"
    ],
    "name:fao_x_preferred":[
        "M\u00fali"
    ],
    "name:fre_x_preferred":[
        "M\u00fali"
    ],
    "name:ger_x_preferred":[
        "M\u00fali"
    ],
    "name:hun_x_preferred":[
        "M\u00fali"
    ],
    "name:nob_x_preferred":[
        "M\u00fali"
    ],
    "name:pol_x_preferred":[
        "M\u00fali"
    ],
    "name:rum_x_preferred":[
        "M\u00fali"
    ],
    "name:swe_x_preferred":[
        "M\u00fali"
    ],
    "name:unk_x_variant":[
        "Mule"
    ],
    "qs_pg:aaroncc":"FO",
    "qs_pg:gn_country":"FO",
    "qs_pg:gn_fcode":"PPL",
    "qs_pg:gn_pop":4,
    "qs_pg:name":"M\u00fali",
    "qs_pg:name_adm0":"F\u00e6r\u00f8erne",
    "qs_pg:name_adm1":"Nor\u00f0oy",
    "qs_pg:photos":62,
    "qs_pg:photos_1k":13,
    "qs_pg:photos_9k":1,
    "qs_pg:photos_9r":2,
    "qs_pg:photos_all":62,
    "qs_pg:photos_sr":2,
    "qs_pg:pop_sr":1,
    "qs_pg:qs_pg_placetype":"locality",
    "qs_pg:qs_pg_placetype_gp":"Town",
    "qs_pg:woe_adm0":23424816,
    "woe:adm0_id":23424816,
    "woe:name_adm0":"F\u00e6r\u00f8erne",
    "woe:name_adm1":"Nor\u00f0oy",
    "woe:placetype":"Town",
    "wof:name":"M\u00fali",
    "wof:placetype":"locality",
    "wof:population":4
},
  "geometry": {"coordinates":[-6.57688,62.35059],"type":"Point"}
}