{
  "type": "Feature",
  "properties": {
    "gn:admin1_code":"NO",
    "gn:admin2_code":"5",
    "gn:asciiname":"Biskupsstod",
    "gn:country_code":"FO",
    "gn:dem":87,
    "gn:feature_class":"P",
    "gn:feature_code":"PPL",
    "gn:name":"Biskupsst\u00f8\u00f0",
    "gn:population":0,
    "gn:timezone":"Atlantic/Faroe",
    "iso:country":"FO",
    "name:und_x_variant":[
        "Biskopst\u00f8",
        "Biskupsst\u00f8\u00f0"
    ],
    "wof:name":"Biskupsstod",
    "wof:placetype":"locality"
},
  "geometry": {"coordinates":[-6.57685,62.22701],"type":"Point"}
}