{
  "type": "Feature",
  "properties": {
    "gn:admin1_code":"ST",
    "gn:asciiname":"Kjalnes",
    "gn:cc2":"FO",
    "gn:country_code":"FO",
    "gn:dem":1,
    "gn:feature_class":"P",
    "gn:feature_code":"PPL",
    "gn:name":"Kjalnes",
    "gn:population":0,
    "gn:timezone":"Atlantic/Faroe",
    "iso:country":"FO",
    "name:und_x_variant":[
        "Keln\u00e6s",
        "K\u00e6ln\u00e6stange",
        "K\u00e6ln\u00e6s",
        "Kjalnes"
    ],
    "wof:name":"Kjalnes",
    "wof:placetype":"locality"
},
  "geometry": {"coordinates":[-6.86667,62.11666999999999],"type":"Point"}
}