{
  "type": "Feature",
  "properties": {
    "iso:country":"FO",
    "name:ara_x_preferred":[
        "\u0645\u0637\u0627\u0631 \u0641\u0627\u063a\u0627\u0631"
    ],
    "name:arz_x_preferred":[
        "\u06a4\u0627\u062c\u0627\u0631 \u0627\u064a\u0631\u067e\u0648\u0631\u062a"
    ],
    "name:cat_x_preferred":[
        "Aeroport de V\u00e1gar"
    ],
    "name:ces_x_preferred":[
        "Leti\u0161t\u011b V\u00e1gar"
    ],
    "name:cym_x_preferred":[
        "Maes Awyr V\u00e1gar"
    ],
    "name:dan_x_preferred":[
        "V\u00e1gar Lufthavn"
    ],
    "name:deu_x_preferred":[
        "Flughafen V\u00e1gar"
    ],
    "name:eng_x_preferred":[
        "V\u00e1gar Airport"
    ],
    "name:eng_x_variant":[
        "FAE",
        "EKVG"
    ],
    "name:epo_x_preferred":[
        "Flughaveno de V\u00e1gar"
    ],
    "name:fao_x_preferred":[
        "V\u00e1ga Floghavn"
    ],
    "name:fas_x_preferred":[
        "\u0641\u0631\u0648\u062f\u06af\u0627\u0647 \u0648\u0627\u06af\u0627\u0631"
    ],
    "name:fin_x_preferred":[
        "V\u00e1garin lentoasema"
    ],
    "name:fra_x_preferred":[
        "A\u00e9roport de V\u00e1gar"
    ],
    "name:heb_x_preferred":[
        "\u05e0\u05de\u05dc \u05d4\u05ea\u05e2\u05d5\u05e4\u05d4 \u05d5\u05d0\u05d5\u05d2\u05e8"
    ],
    "name:hrv_x_preferred":[
        "Zra\u010dna luka V\u00e1gar"
    ],
    "name:hun_x_preferred":[
        "V\u00e1gari rep\u00fcl\u0151t\u00e9r"
    ],
    "name:ind_x_preferred":[
        "Bandar Udara V\u00e1gar"
    ],
    "name:isl_x_preferred":[
        "V\u00e1gaflugv\u00f6llur"
    ],
    "name:jpn_x_preferred":[
        "\u30f4\u30a9\u30fc\u30a2\u30eb\u7a7a\u6e2f"
    ],
    "name:kor_x_preferred":[
        "\ubcf4\uac00\ub974 \uacf5\ud56d"
    ],
    "name:lav_x_preferred":[
        "Voaras lidosta"
    ],
    "name:lit_x_preferred":[
        "Vagaro oro uostas"
    ],
    "name:msa_x_preferred":[
        "Lapangan Terbang Vagar"
    ],
    "name:nld_x_preferred":[
        "Luchthaven V\u00e1gar"
    ],
    "name:nob_x_preferred":[
        "V\u00e1gar lufthavn"
    ],
    "name:pol_x_preferred":[
        "Port lotniczy V\u00e1gar"
    ],
    "name:ron_x_preferred":[
        "Aeroportul V\u00e1gar"
    ],
    "name:rus_x_preferred":[
        "\u0412\u0430\u0433\u0430\u0440"
    ],
    "name:spa_x_preferred":[
        "Aeropuerto de V\u00e1gar"
    ],
    "name:srp_x_preferred":[
        "\u0410\u0435\u0440\u043e\u0434\u0440\u043e\u043c \u0412\u0430\u0433\u0430\u0440"
    ],
    "name:swe_x_preferred":[
        "V\u00e1gar flygplats"
    ],
    "name:tgk_x_preferred":[
        "\u0424\u0443\u0440\u0443\u0434\u0433\u043e\u04b3\u0438 \u0432\u043e\u0433\u043e\u0440"
    ],
    "name:tur_x_preferred":[
        "V\u00e1gar Havaalan\u0131"
    ],
    "name:ukr_x_preferred":[
        "\u0412\u0430\u0433\u0430\u0440"
    ],
    "name:vie_x_preferred":[
        "S\u00e2n bay V\u00e1gar"
    ],
    "name:zho_x_preferred":[
        "\u6c83\u683c\u6a5f\u5834"
    ],
    "oa:elevation_ft":"280",
    "oa:type":"medium_airport",
    "wd:wordcount":1046,
    "woe:hierarchy":{
        "country_id":23424816,
        "planet_id":1,
        "state_id":24549694
    },
    "wof:name":"Vagar Airport",
    "wof:placetype":"campus"
},
  "geometry": {"coordinates":[-7.277222,62.063611],"type":"Point"}
}