{
  "type": "Feature",
  "properties": {
    "iso:country":"FO",
    "name:cat_x_preferred":[
        "Aeroport de V\u00e1gar"
    ],
    "name:ces_x_preferred":[
        "Leti\u0161t\u011b V\u00e1gar"
    ],
    "name:dan_x_preferred":[
        "V\u00e1gar Lufthavn"
    ],
    "name:deu_x_preferred":[
        "Flughafen V\u00e1gar"
    ],
    "name:epo_x_preferred":[
        "Flughaveno de V\u00e1gar"
    ],
    "name:fao_x_preferred":[
        "V\u00e1ga Floghavn"
    ],
    "name:fas_x_preferred":[
        "\u0641\u0631\u0648\u062f\u06af\u0627\u0647 \u0648\u0627\u06af\u0627\u0631"
    ],
    "name:fin_x_preferred":[
        "V\u00e1garin lentoasema"
    ],
    "name:fra_x_preferred":[
        "A\u00e9roport de V\u00e1gar"
    ],
    "name:spa_x_preferred":[
        "Aeropuerto de V\u00e1gar"
    ],
    "oa:elevation_ft":"280",
    "oa:type":"medium_airport",
    "wd:wordcount":1046,
    "woe:hierarchy":{
        "country_id":23424816,
        "planet_id":1,
        "state_id":24549694
    },
    "wof:name":"Vagar Airport",
    "wof:placetype":"campus"
},
  "geometry": {"coordinates":[-7.2772222222222,62.063611111111],"type":"Point"}
}