{
  "type": "Feature",
  "properties": {
    "gn:admin1_code":"ST",
    "gn:admin2_code":"29",
    "gn:asciiname":"Midgerdi",
    "gn:country_code":"FO",
    "gn:dem":30,
    "gn:feature_class":"P",
    "gn:feature_code":"PPL",
    "gn:name":"Mi\u00f0ger\u00f0i",
    "gn:population":0,
    "gn:timezone":"Atlantic/Faroe",
    "iso:country":"FO",
    "name:und_x_variant":[
        "Midjord",
        "Mi\u00f0ger\u00f0i"
    ],
    "wof:name":"Midgerdi",
    "wof:placetype":"locality"
},
  "geometry": {"coordinates":[-6.88422,62.11912],"type":"Point"}
}