{
  "type": "Feature",
  "properties": {
    "gn:admin1_code":"ST",
    "gn:admin2_code":"18",
    "gn:asciiname":"Toftir",
    "gn:country_code":"FO",
    "gn:dem":372,
    "gn:feature_class":"P",
    "gn:feature_code":"PPL",
    "gn:name":"Toftir",
    "gn:population":0,
    "gn:timezone":"Atlantic/Faroe",
    "iso:country":"FO",
    "wof:name":"Toftir",
    "wof:placetype":"locality"
},
  "geometry": {"coordinates":[-6.93333,62.15],"type":"Point"}
}