{
  "type": "Feature",
  "properties": {
    "gn:admin1_code":"ST",
    "gn:admin2_code":"18",
    "gn:asciiname":"Toftir",
    "gn:country_code":"FO",
    "gn:dem":372,
    "gn:feature_class":"P",
    "gn:feature_code":"PPL",
    "gn:name":"Toftir",
    "gn:population":0,
    "gn:timezone":"Atlantic/Faroe",
    "iso:country":"FO",
    "name:ara_x_preferred":[
        "\u062a\u0648\u0641\u062a\u064a\u0631"
    ],
    "name:arz_x_preferred":[
        "\u062a\u0648\u0641\u062a\u064a\u0631"
    ],
    "name:cat_x_preferred":[
        "Toftir"
    ],
    "name:dan_x_preferred":[
        "Toftir"
    ],
    "name:deu_x_preferred":[
        "Toftir"
    ],
    "name:fao_x_preferred":[
        "Toftir"
    ],
    "name:fin_x_preferred":[
        "Toftir"
    ],
    "name:fra_x_preferred":[
        "Toftir"
    ],
    "name:glv_x_preferred":[
        "Toftir"
    ],
    "name:hun_x_preferred":[
        "Toftir"
    ],
    "name:isl_x_preferred":[
        "Toftir"
    ],
    "name:ita_x_preferred":[
        "Toftir"
    ],
    "name:kor_x_preferred":[
        "\ud1a0\ud504\ud2f0\ub974"
    ],
    "name:lit_x_preferred":[
        "Toftiras"
    ],
    "name:nld_x_preferred":[
        "Toftir"
    ],
    "name:nor_x_preferred":[
        "Toftir"
    ],
    "name:pol_x_preferred":[
        "Toftir"
    ],
    "name:ron_x_preferred":[
        "Toftir"
    ],
    "name:rus_x_preferred":[
        "\u0422\u043e\u0444\u0442\u0438\u0440"
    ],
    "name:slk_x_preferred":[
        "Toftir"
    ],
    "name:spa_x_preferred":[
        "Toftir"
    ],
    "name:swe_x_preferred":[
        "Toftir"
    ],
    "wof:name":"Toftir",
    "wof:placetype":"locality"
},
  "geometry": {"coordinates":[-6.93333,62.15],"type":"Point"}
}