{
  "type": "Feature",
  "properties": {
    "gn:admin1_code":"SU",
    "gn:admin2_code":"44",
    "gn:asciiname":"Skalar",
    "gn:country_code":"FO",
    "gn:dem":88,
    "gn:feature_class":"P",
    "gn:feature_code":"PPL",
    "gn:name":"Sk\u00e1lar",
    "gn:population":0,
    "gn:timezone":"Atlantic/Faroe",
    "iso:country":"FO",
    "wof:name":"Skalar",
    "wof:placetype":"locality"
},
  "geometry": {"coordinates":[-6.95709,61.60302],"type":"Point"}
}